Workbook

Sheet Dashboard
A1: DQLab Store – Dashboard Sales Performance 2009-2012
A3: Net Revenue (Rp juta) | B3: Profit Proxy (Rp juta) | C3: Return Rate (by value) | D3: Diskon % Gross Profit | E3: Δ Profit Skenario (Rp juta) | F3: Break-even Volume Loss
A4: =Kategori!H8 -> 16415676168 | B4: =Kategori!I8 -> 4.3280813e+09 | C4: =Kategori!E8 -> 0.10934137 | D4: =Diskon!E43 -> 0.16452722 | E4: =Ringkasan!D30 -> 1.8107034e+08 | F4: =Ringkasan!A40 -> 0.13059387
A5: =Ringkasan!B15 -> Diskon TIDAK menaikkan qty/sales di kategori manapun → diskon saat ini menggerus margin tanpa imbal volume.

Sheet Dokumentasi
A1: Dokumentasi Analisis – DQLab Store Sales Performance 2009–2012
A2: Portofolio junior data analyst · dikerjakan 100% di Excel (formula hidup, bukan hardcode)
A5: 1. Tujuan & pertanyaan bisnis
A6: Master question | B6: Bagaimana DQLab Store mengalokasikan ulang resource ke kategori yang profitable dan mengoptimalkan strategi diskon untuk memaksimalkan profit?
A7: Sub-question | B7: (1) Kategori mana paling profitable (revenue, margin, return risk)? (2) Apakah diskon efektif atau menggerus margin? (3) Kategori mana paling sensitif terhadap diskon? (4) Rekomendasi: fokus kategori + diskon optimal per kategori.
A8: Output | B8: Alokasi budget marketing (%) per kategori · kebijakan diskon · estimasi dampak profit (Rp).
A10: 2. Data
A11: Sumber | B11: dqlab_sales.xlsx: 5.499 baris × 10 kolom (order_id, order_status, customer, order_date, order_quantity, sales, discount, discount_value, product_category, product_sub_category). Periode 1 Jan 2009 – 30 Des 2012; 3 kategori, 17 sub-kategori. Mata uang IDR.
A12: Cek kualitas | B12: • Tidak ada nilai kosong. • discount_value = sales × discount (0 selisih di seluruh baris). • Status: 4.924 Finished, 572 Returned, 3 Cancelled (semua Office Supplies, total ±Rp39 juta) → Cancelled dikeluarkan dari analisis. • 3 order_id muncul ganda (pasangan Finished+Cancelled, dan 1 id beda sub-kategori) → bukan duplikat baris penuh, dibiarkan. • 3 order Furniture berdiskon 11%/16%/17% (di atas pola 0–10%) → dipertahankan, masuk bucket 7%+. • Diskon tersebar merata 0–10% (±500 order per level).
A13: KETERBATASAN UTAMA | B13: Dataset TIDAK memuat biaya (HPP/COGS) sehingga profit sebenarnya tidak bisa dihitung. Saya memakai "Profit Proxy" = Sales Finished × Gross Margin asumsi (30% flat, sel biru di sheet Asumsi) − Diskon. Ganti margin dengan data asli perusahaan; seluruh sheet akan menghitung ulang.
A15: 3. Definisi metrik
A16: Gross Sales | B16: Σ sales order Finished + Returned.
A17: Net Revenue | B17: Σ (sales − discount_value) hanya Order Finished. Order Returned dianggap di-refund (revenue 0).
A18: Return Rate | B18: Returned Sales ÷ Gross Sales (by value). Sheet Diskon memakai by jumlah order.
A19: Profit Proxy | B19: Sales Finished × Gross Margin − discount_value (Finished). Returned/Cancelled = 0 (asumsi barang kembali ke stok, tanpa biaya logistik).
A20: Margin Proxy | B20: Profit Proxy ÷ Gross Sales → return ikut menekan margin.
A21: Sensitivitas diskon | B21: Korelasi Pearson antara % diskon vs qty/order dan vs sales/order per kategori; "Sensitif" bila |r| ≥ 0,10 (ambang di sheet Asumsi). Dilengkapi lift 7%+ vs 0%.
A23: 4. Langkah kerja & struktur workbook
A24: Dashboard | B24: Halaman depan: 6 KPI + 6 chart (ringkasan visual dari sheet lain).
A25: Data | B25: Data mentah (kolom A–J) + 12 kolom helper berformula (K–V): Year, flag Finished/Returned/Valid, bucket diskon, Net Revenue, Profit Proxy, diskon baru (setelah cap), flag terdampak, penghematan diskon, profit skenario.
A26: Asumsi | B26: Semua input: gross margin per kategori, cap diskon per kategori, volume loss, ambang sensitivitas (sel biru berlatar kuning).
A27: Kategori | B27: SUMIFS/COUNTIFS per kategori & sub-kategori, tren tahunan + 3 chart.
A28: Diskon | B28: Qty, sales/order & return rate per bucket diskon (AVERAGEIFS/COUNTIFS), korelasi manual via SUMPRODUCT, biaya diskon + 2 chart.
A29: Ringkasan | B29: Jawaban atas sub-question, alokasi marketing, cap diskon, dampak profit & uji sensitivitas asumsi. Semua sel = link ke sheet analisis.
A30: Verifikasi | B30: Workbook di-recalc (0 error dari 66 ribu formula) dan angka kunci dicocokkan dengan perhitungan independen di pandas (profit baseline/skenario, penghematan, korelasi: selisih 0).
A32: 5. Temuan utama (angka sesuai asumsi margin 30%; lihat sheet Ringkasan untuk nilai terkini)
A33: Q1 Kategori | B33: Technology paling profitable (profit proxy ±Rp1,65 miliar, 38% share), diikuti Furniture (±Rp1,51 miliar, 35%) dan Office Supplies (±Rp1,16 miliar, 27%). Office Supplies punya order terbanyak (±3.060) tapi profit per order hanya ±Rp0,38 juta vs ±Rp1,3 juta di dua kategori lain → volume tinggi ≠ profit tinggi. Return rate relatif seragam (10,5%–11,8%), tertinggi di Office Supplies. Margin proxy 21,9%–22,7% hampir sama karena margin asumsi flat – perbedaan nyata baru muncul bila HPP per kategori tersedia.
A34: Q2 Efektivitas diskon | B34: Diskon menghabiskan ±15–17% gross profit di setiap kategori (total ±Rp852 juta selama 4 tahun) tetapi qty/order dan sales/order praktis sama di semua level diskon (|r| ≤ 0,06). Artinya diskon saat ini tidak membeli volume tambahan → menggerus margin.
A35: Q3 Sensitivitas | B35: Tidak ada kategori yang "sensitif" (semua |r| < 0,10). Furniture punya korelasi sales/order paling negatif (−0,059; sangat kecil), sedikit mengarah ke arah yang salah.
A36: Q4 Rekomendasi | B36: • Alokasi marketing ≈ Technology 38% · Furniture 35% · Office Supplies 27% (proporsional dengan share profit; Office Supplies perlu pendekatan hemat biaya/upsell bundling karena profit per order rendah). • Cap diskon: Furniture 3%, Technology 5%, Office Supplies 5% (dengan A/B test bertahap, mulai dari Furniture karena biaya diskon per order terbesar).
A37: Dampak profit | B37: Dengan cap di atas dan asumsi 5% volume hilang di pesanan terdampak: profit +±Rp181 juta (+4,2%) selama 4 tahun (≈Rp45 juta/tahun); tanpa volume loss +Rp293 juta (+6,8%). Break-even volume loss ±13%: profit tetap positif selama volume yang hilang < 13%.
A39: 6. Asumsi, risiko & langkah lanjutan
A40: Kausalitas | B40: Analisis ini observasional. Diskon mungkin diberikan secara acak sehingga mendekati eksperimen alami, tapi tidak ada jaminan; belum memodelkan efek jangka panjang (loyalitas, kompetitor). Validasi lewat A/B test sebelum roll-out penuh.
A41: Return vs diskon | B41: Ada indikasi return rate lebih rendah pada diskon tinggi untuk Office Supplies & Technology (mis. Office: 13,5% di 0% → 8,6% di 7%+). Efek ini tidak masuk skenario; jika nyata, ia mengurangi penghematan dari pemotongan diskon. Perlu diuji lebih lanjut (kemungkinan noise: sampel bucket 0% hanya 107–267 order).
A42: Skala & tren | B42: Data berhenti 2012, jadi angka Rp adalah basis historis, bukan proyeksi. Net revenue tahunan relatif datar 2009–2012 (lihat chart tren).
A43: Lanjutan | B43: (1) Isi HPP/margin asli per kategori & sub-kategori. (2) Analisis pelanggan (repeat vs one-time). (3) Dampak diskon per sub-kategori.

Sheet Ringkasan
A1: DQLab Store – Ringkasan Eksekutif & Rekomendasi
A2: Semua angka = formula yang terhubung ke sheet analisis. Rp juta kecuali dinyatakan lain. Profit = PROXY (asumsi margin di sheet Asumsi).
A4: 1. Kategori mana paling profitable?
A5: Kategori | B5: Net Revenue (Rp juta) | C5: Profit Proxy (Rp juta) | D5: Margin Proxy | E5: Return Rate | F5: Profit / Order (Rp juta) | G5: Peringkat Profit
A6: Furniture | B6: =Kategori!H5 -> 5667179940 | C6: =Kategori!I5 -> 1508841658 | D6: =Kategori!J5 -> 0.22669741 | E6: =Kategori!E5 -> 0.1074662 | F6: =Kategori!K5 -> 1308622.4 | G6: =RANK(C6,$C$6:$C$8) -> 2
A7: Office Supplies | B7: =Kategori!H6 -> 4444296931 | C7: =Kategori!I6 -> 1164396937 | D7: =Kategori!J6 -> 0.21930936 | E7: =Kategori!E6 -> 0.11749193 | F7: =Kategori!K6 -> 380149.18 | G7: =RANK(C7,$C$6:$C$8) -> 3
A8: Technology | B8: =Kategori!H7 -> 6304199297 | C8: =Kategori!I7 -> 1.6548427e+09 | D8: =Kategori!J7 -> 0.22294173 | E8: =Kategori!E7 -> 0.10519281 | F8: =Kategori!K7 -> 1292845.9 | G8: =RANK(C8,$C$6:$C$8) -> 1
A10: 2. Apakah diskon efektif? Kategori mana yang sensitif?
A11: Kategori | B11: Diskon Diberikan (Rp juta) | C11: % dari Sales | D11: % dari Gross Profit | E11: r (disc, qty) | F11: r (disc, sales/order) | G11: Sensitivitas
A12: Furniture | B12: =Diskon!B40 -> 273303320 | C12: =Diskon!C40 -> 0.046006917 | D12: =Diskon!E40 -> 0.15335639 | E12: =Diskon!K34 -> -0.02825613 | F12: =Diskon!L34 -> -0.058996309 | G12: =Diskon!M34 -> Tidak sensitif
A13: Office Supplies | B13: =Diskon!B41 -> 241274489 | C13: =Diskon!C41 -> 0.051493077 | D13: =Diskon!E41 -> 0.17164359 | E13: =Diskon!K35 -> -0.0066440998 | F13: =Diskon!L35 -> 0.0033705514 | G13: =Diskon!M35 -> Tidak sensitif
A14: Technology | B14: =Diskon!B42 -> 337738655 | C14: =Diskon!C42 -> 0.050849414 | D14: =Diskon!E42 -> 0.16949805 | E14: =Diskon!K36 -> -0.013007729 | F14: =Diskon!L36 -> 0.010238092 | G14: =Diskon!M36 -> Tidak sensitif
A15: Kesimpulan | B15: =IF(COUNTIF(G12:G14,"Tidak sensitif")=3,"Diskon TIDAK menaikkan qty/sales di kategori manapun → diskon saat ini menggerus margin tanpa imbal volume.","Ada kategori yang sensitif terhadap diskon – lihat sheet Diskon.") -> Diskon TIDAK menaikkan qty/sales di kategori manapun → diskon saat ini menggerus margin tanpa imbal volume.
A17: 3. Rekomendasi: alokasi marketing & kebijakan diskon
A18: Kategori | B18: Alokasi Marketing (% budget) | C18: Share Net Revenue | D18: Diskon rata-rata saat ini (% sales) | E18: Cap Diskon Rekomendasi | F18: Diskon Maks. Historis
A19: Furniture | B19: =Kategori!M5 -> 0.34861675 | C19: =Kategori!L5 -> 0.34522976 | D19: =Kategori!G5 -> 0.046006917 | E19: =Asumsi!C5 -> 0.03 | F19: =SUMPRODUCT(MAX((Data!$I$2:$I$5500=$A19)*Data!$G$2:$G$5500)) -> 0.17
A20: Office Supplies | B20: =Kategori!M6 -> 0.26903305 | C20: =Kategori!L6 -> 0.27073493 | D20: =Kategori!G6 -> 0.051493077 | E20: =Asumsi!C6 -> 0.05 | F20: =SUMPRODUCT(MAX((Data!$I$2:$I$5500=$A20)*Data!$G$2:$G$5500)) -> 0.1
A21: Technology | B21: =Kategori!M7 -> 0.38235019 | C21: =Kategori!L7 -> 0.38403531 | D21: =Kategori!G7 -> 0.050849414 | E21: =Asumsi!C7 -> 0.05 | F21: =SUMPRODUCT(MAX((Data!$I$2:$I$5500=$A21)*Data!$G$2:$G$5500)) -> 0.1
A22: Total | B22: =SUM(B19:B21) -> 1 | C22: =SUM(C19:C21) -> 1
A23: Alokasi marketing = share profit proxy tiap kategori (profit sudah net diskon & return, jadi risiko return otomatis terhitung). Anggaran saat ini tidak ada di dataset, sehingga alokasi ini adalah target, bukan selisih dari kondisi sekarang.
A25: 4. Expected profit impact (Order Finished, 2009–2012 sebagai basis historis)
A26: Kategori | B26: Profit Baseline (Rp juta) | C26: Profit Skenario (Rp juta) | D26: Δ Profit (Rp juta) | E26: Δ % | F26: Penghematan Diskon Gross (Rp juta) | G26: Biaya Volume Loss (Rp juta)
A27: Furniture | B27: =SUMIFS(Data!$Q$2:$Q$5500,Data!$I$2:$I$5500,$A27) -> 1508841658 | C27: =SUMIFS(Data!$V$2:$V$5500,Data!$I$2:$I$5500,$A27) -> 1.5964214e+09 | D27: =C27-B27 -> 87579717 | E27: =D27/B27 -> 0.058044339 | F27: =SUMIFS(Data!$T$2:$T$5500,Data!$I$2:$I$5500,$A27) -> 1.3305933e+08 | G27: =F27-D27 -> 45479613
A28: Office Supplies | B28: =SUMIFS(Data!$Q$2:$Q$5500,Data!$I$2:$I$5500,$A28) -> 1164396937 | C28: =SUMIFS(Data!$V$2:$V$5500,Data!$I$2:$I$5500,$A28) -> 1.2047221e+09 | D28: =C28-B28 -> 40325144 | E28: =D28/B28 -> 0.034631785 | F28: =SUMIFS(Data!$T$2:$T$5500,Data!$I$2:$I$5500,$A28) -> 67322124 | G28: =F28-D28 -> 26996980
A29: Technology | B29: =SUMIFS(Data!$Q$2:$Q$5500,Data!$I$2:$I$5500,$A29) -> 1.6548427e+09 | C29: =SUMIFS(Data!$V$2:$V$5500,Data!$I$2:$I$5500,$A29) -> 1.7080082e+09 | D29: =C29-B29 -> 53165477 | E29: =D29/B29 -> 0.032127208 | F29: =SUMIFS(Data!$T$2:$T$5500,Data!$I$2:$I$5500,$A29) -> 93023965 | G29: =F29-D29 -> 39858487
A30: Total | B30: =SUM(B27:B29) -> 4.3280813e+09 | C30: =SUM(C27:C29) -> 4.5091517e+09 | D30: =SUM(D27:D29) -> 1.8107034e+08 | E30: =D30/B30 -> 0.041836168 | F30: =SUM(F27:F29) -> 2.9340542e+08 | G30: =SUM(G27:G29) -> 1.1233508e+08
A31: Rata-rata per tahun (4 tahun) | D31: =D30/4 -> 45267585
A32: Asumsi skenario: diskon dipotong ke cap per kategori; pesanan yang diskonnya dipotong kehilangan volume sebesar parameter "volume loss" (sheet Asumsi).
A34: 5. Uji sensitivitas asumsi volume loss
A35: Volume loss pada pesanan terdampak | B35: Δ Profit Total (Rp juta) | C35: Δ % vs Baseline
A36: 0 | B36: =$F$30-A36*$B$41 -> 2.9340542e+08 | C36: =B36/$B$30 -> 0.067791106
A37: 0.05 | B37: =$F$30-A37*$B$41 -> 1.8107035e+08 | C37: =B37/$B$30 -> 0.041836172
A38: 0.1 | B38: =$F$30-A38*$B$41 -> 68735291 | C38: =B38/$B$30 -> 0.015881238
A39: 0.2 | B39: =$F$30-A39*$B$41 -> -1.5593484e+08 | C39: =B39/$B$30 -> -0.036028629
A40: =F30/B41 -> 0.13059387 | B40: =F30-A40*B41 -> 0 | C40: =B40/B30 -> 0
A41: Profit (harga baru) dari pesanan terdampak (Rp juta) | B41: =SUMIFS(Data!$U$2:$U$5500,Data!$S$2:$S$5500,1) -> 2.2467013e+09
A42: Break-even = persentase volume yang boleh hilang pada pesanan terdampak sebelum penghematan diskon habis. Semakin tinggi, semakin aman kebijakan cap diskon.

Sheet Asumsi
A1: Asumsi & Parameter (sel biru/kuning = bisa diubah)
A2: Seluruh analisis profit & skenario mengacu ke sel-sel ini. Ubah nilai → semua sheet otomatis menghitung ulang.
A4: Kategori | B4: Gross margin % (ASUMSI) | C4: Cap diskon rekomendasi
A5: Furniture | B5: 0.3 | C5: 0.03
A6: Office Supplies | B6: 0.3 | C6: 0.05
A7: Technology | B7: 0.3 | C7: 0.05
A9: Parameter skenario
A10: Volume loss pada pesanan yang diskonnya dipotong | B10: 0.05
A11: Ambang |korelasi| untuk dianggap "sensitif" terhadap diskon | B11: 0.1
A14: CATATAN & SUMBER ASUMSI
A15: 1. Gross margin 30% flat untuk semua kategori adalah ASUMSI saya (dataset TIDAK memuat HPP/COGS). Ganti dengan angka margin asli perusahaan. Dengan margin sama, perbedaan profit antar kategori hanya berasal dari revenue, diskon & return.
A16: 2. Cap diskon (3% / 5% / 5%) adalah rekomendasi berbasis temuan di sheet Diskon (diskon tidak menaikkan qty/sales); bisa diubah untuk uji skenario lain.
A17: 3. Volume loss 5% adalah haircut konservatif: data historis menunjukkan elastisitas ≈ 0, tapi pemotongan diskon di luar kisaran historis (>0) tetap kita beri buffer risiko. Lihat sensitivitas 0%–20% & break-even di sheet Ringkasan.
A18: 4. Ambang korelasi 0,10 = aturan praktis (efek kecil secara praktis); bukan hasil uji formal.

Sheet Kategori
A1: Analisis Kategori: Revenue, Margin, Return Risk
A2: Semua angka dalam Rp juta kecuali dinyatakan lain. Order Cancelled (3 baris) dikeluarkan. Net Revenue & Profit Proxy hanya dari Order Finished (Returned dianggap refund).
A3: 1. Ringkasan per kategori
A4: Kategori | B4: Orders (Finished+ Returned) | C4: Gross Sales (Rp juta) | D4: Returned Sales (Rp juta) | E4: Return Rate (by value) | F4: Diskon Diberikan (Rp juta) | G4: Diskon % Sales Finished | H4: Net Revenue (Rp juta) | I4: Profit Proxy (Rp juta) | J4: Margin Proxy (% Gross Sales) | K4: Profit / Order (Rp juta) | L4: Share Net Revenue | M4: Share Profit
A5: Furniture | B5: =COUNTIFS(Data!$I$2:$I$5500,$A5,Data!$L$2:$L$5500,1)+COUNTIFS(Data!$I$2:$I$5500,$A5,Data!$M$2:$M$5500,1) -> 1153 | C5: =SUMIFS(Data!$F$2:$F$5500,Data!$I$2:$I$5500,$A5,Data!$L$2:$L$5500,1)+SUMIFS(Data!$F$2:$F$5500,Data!$I$2:$I$5500,$A5,Data!$M$2:$M$5500,1) -> 6655751588 | D5: =SUMIFS(Data!$F$2:$F$5500,Data!$I$2:$I$5500,$A5,Data!$M$2:$M$5500,1) -> 715268328 | E5: =IFERROR(D5/C5,0) -> 0.1074662 | F5: =SUMIFS(Data!$H$2:$H$5500,Data!$I$2:$I$5500,$A5,Data!$L$2:$L$5500,1) -> 273303320 | G5: =IFERROR(F5/SUMIFS(Data!$F$2:$F$5500,Data!$I$2:$I$5500,$A5,Data!$L$2:$L$5500,1),0) -> 0.046006917 | H5: =SUMIFS(Data!$P$2:$P$5500,Data!$I$2:$I$5500,$A5) -> 5667179940 | I5: =SUMIFS(Data!$Q$2:$Q$5500,Data!$I$2:$I$5500,$A5) -> 1508841658 | J5: =IFERROR(I5/C5,0) -> 0.22669741 | K5: =IFERROR(I5/B5,0) -> 1308622.4 | L5: =H5/H$8 -> 0.34522976 | M5: =I5/I$8 -> 0.34861675
A6: Office Supplies | B6: =COUNTIFS(Data!$I$2:$I$5500,$A6,Data!$L$2:$L$5500,1)+COUNTIFS(Data!$I$2:$I$5500,$A6,Data!$M$2:$M$5500,1) -> 3063 | C6: =SUMIFS(Data!$F$2:$F$5500,Data!$I$2:$I$5500,$A6,Data!$L$2:$L$5500,1)+SUMIFS(Data!$F$2:$F$5500,Data!$I$2:$I$5500,$A6,Data!$M$2:$M$5500,1) -> 5309380840 | D6: =SUMIFS(Data!$F$2:$F$5500,Data!$I$2:$I$5500,$A6,Data!$M$2:$M$5500,1) -> 623809420 | E6: =IFERROR(D6/C6,0) -> 0.11749193 | F6: =SUMIFS(Data!$H$2:$H$5500,Data!$I$2:$I$5500,$A6,Data!$L$2:$L$5500,1) -> 241274489 | G6: =IFERROR(F6/SUMIFS(Data!$F$2:$F$5500,Data!$I$2:$I$5500,$A6,Data!$L$2:$L$5500,1),0) -> 0.051493077 | H6: =SUMIFS(Data!$P$2:$P$5500,Data!$I$2:$I$5500,$A6) -> 4444296931 | I6: =SUMIFS(Data!$Q$2:$Q$5500,Data!$I$2:$I$5500,$A6) -> 1164396937 | J6: =IFERROR(I6/C6,0) -> 0.21930936 | K6: =IFERROR(I6/B6,0) -> 380149.18 | L6: =H6/H$8 -> 0.27073493 | M6: =I6/I$8 -> 0.26903305
A7: Technology | B7: =COUNTIFS(Data!$I$2:$I$5500,$A7,Data!$L$2:$L$5500,1)+COUNTIFS(Data!$I$2:$I$5500,$A7,Data!$M$2:$M$5500,1) -> 1280 | C7: =SUMIFS(Data!$F$2:$F$5500,Data!$I$2:$I$5500,$A7,Data!$L$2:$L$5500,1)+SUMIFS(Data!$F$2:$F$5500,Data!$I$2:$I$5500,$A7,Data!$M$2:$M$5500,1) -> 7422758843 | D7: =SUMIFS(Data!$F$2:$F$5500,Data!$I$2:$I$5500,$A7,Data!$M$2:$M$5500,1) -> 780820891 | E7: =IFERROR(D7/C7,0) -> 0.10519281 | F7: =SUMIFS(Data!$H$2:$H$5500,Data!$I$2:$I$5500,$A7,Data!$L$2:$L$5500,1) -> 337738655 | G7: =IFERROR(F7/SUMIFS(Data!$F$2:$F$5500,Data!$I$2:$I$5500,$A7,Data!$L$2:$L$5500,1),0) -> 0.050849414 | H7: =SUMIFS(Data!$P$2:$P$5500,Data!$I$2:$I$5500,$A7) -> 6304199297 | I7: =SUMIFS(Data!$Q$2:$Q$5500,Data!$I$2:$I$5500,$A7) -> 1.6548427e+09 | J7: =IFERROR(I7/C7,0) -> 0.22294173 | K7: =IFERROR(I7/B7,0) -> 1292845.9 | L7: =H7/H$8 -> 0.38403531 | M7: =I7/I$8 -> 0.38235019
A8: Total | B8: =SUM(B5:B7) -> 5496 | C8: =SUM(C5:C7) -> 19387891271 | D8: =SUM(D5:D7) -> 2119898639 | E8: =D8/C8 -> 0.10934137 | F8: =SUM(F5:F7) -> 852316464 | G8: =F8/SUMIFS(Data!$F$2:$F$5500,Data!$L$2:$L$5500,1) -> 0.049358167 | H8: =SUM(H5:H7) -> 16415676168 | I8: =SUM(I5:I7) -> 4.3280813e+09 | J8: =I8/C8 -> 0.22323631 | K8: =I8/B8 -> 787496.6 | L8: =SUM(L5:L7) -> 1 | M8: =SUM(M5:M7) -> 1
A9: Profit Proxy = Sales Finished × Gross Margin (sheet Asumsi) − Diskon. Margin Proxy = Profit Proxy ÷ Gross Sales (Finished+Returned), sehingga return ikut menurunkan margin.
A11: 2. Sub-kategori (diurutkan berdasarkan profit proxy)
A12: Kategori | B12: Sub-kategori | C12: Orders | D12: Gross Sales (Rp juta) | E12: Return Rate (by value) | F12: Net Revenue (Rp juta) | G12: Profit Proxy (Rp juta) | H12: Margin Proxy | I12: Profit / Order (Rp juta) | J12: Peringkat Profit
A13: Technology | B13: Office Machines | C13: =COUNTIFS(Data!$I$2:$I$5500,$A13,Data!$J$2:$J$5500,$B13,Data!$L$2:$L$5500,1)+COUNTIFS(Data!$I$2:$I$5500,$A13,Data!$J$2:$J$5500,$B13,Data!$M$2:$M$5500,1) -> 234 | D13: =SUMIFS(Data!$F$2:$F$5500,Data!$I$2:$I$5500,$A13,Data!$J$2:$J$5500,$B13,Data!$L$2:$L$5500,1)+SUMIFS(Data!$F$2:$F$5500,Data!$I$2:$I$5500,$A13,Data!$J$2:$J$5500,$B13,Data!$M$2:$M$5500,1) -> 2992042700 | E13: =IFERROR(SUMIFS(Data!$F$2:$F$5500,Data!$I$2:$I$5500,$A13,Data!$J$2:$J$5500,$B13,Data!$M$2:$M$5500,1)/D13,0) -> 0.095164464 | F13: =SUMIFS(Data!$P$2:$P$5500,Data!$I$2:$I$5500,$A13,Data!$J$2:$J$5500,$B13) -> 2576974017 | G13: =SUMIFS(Data!$Q$2:$Q$5500,Data!$I$2:$I$5500,$A13,Data!$J$2:$J$5500,$B13) -> 681859425 | H13: =IFERROR(G13/D13,0) -> 0.22789094 | I13: =IFERROR(G13/C13,0) -> 2913929.2 | J13: =RANK(G13,$G$13:$G$29) -> 1
A14: Furniture | B14: Chairs & Chairmats | C14: =COUNTIFS(Data!$I$2:$I$5500,$A14,Data!$J$2:$J$5500,$B14,Data!$L$2:$L$5500,1)+COUNTIFS(Data!$I$2:$I$5500,$A14,Data!$J$2:$J$5500,$B14,Data!$M$2:$M$5500,1) -> 301 | D14: =SUMIFS(Data!$F$2:$F$5500,Data!$I$2:$I$5500,$A14,Data!$J$2:$J$5500,$B14,Data!$L$2:$L$5500,1)+SUMIFS(Data!$F$2:$F$5500,Data!$I$2:$I$5500,$A14,Data!$J$2:$J$5500,$B14,Data!$M$2:$M$5500,1) -> 2796723780 | E14: =IFERROR(SUMIFS(Data!$F$2:$F$5500,Data!$I$2:$I$5500,$A14,Data!$J$2:$J$5500,$B14,Data!$M$2:$M$5500,1)/D14,0) -> 0.076948221 | F14: =SUMIFS(Data!$P$2:$P$5500,Data!$I$2:$I$5500,$A14,Data!$J$2:$J$5500,$B14) -> 2461315072 | G14: =SUMIFS(Data!$Q$2:$Q$5500,Data!$I$2:$I$5500,$A14,Data!$J$2:$J$5500,$B14) -> 654250470 | H14: =IFERROR(G14/D14,0) -> 0.2339346 | I14: =IFERROR(G14/C14,0) -> 2173589.6 | J14: =RANK(G14,$G$13:$G$29) -> 2
A15: Furniture | B15: Tables | C15: =COUNTIFS(Data!$I$2:$I$5500,$A15,Data!$J$2:$J$5500,$B15,Data!$L$2:$L$5500,1)+COUNTIFS(Data!$I$2:$I$5500,$A15,Data!$J$2:$J$5500,$B15,Data!$M$2:$M$5500,1) -> 180 | D15: =SUMIFS(Data!$F$2:$F$5500,Data!$I$2:$I$5500,$A15,Data!$J$2:$J$5500,$B15,Data!$L$2:$L$5500,1)+SUMIFS(Data!$F$2:$F$5500,Data!$I$2:$I$5500,$A15,Data!$J$2:$J$5500,$B15,Data!$M$2:$M$5500,1) -> 1823721028 | E15: =IFERROR(SUMIFS(Data!$F$2:$F$5500,Data!$I$2:$I$5500,$A15,Data!$J$2:$J$5500,$B15,Data!$M$2:$M$5500,1)/D15,0) -> 0.1160121 | F15: =SUMIFS(Data!$P$2:$P$5500,Data!$I$2:$I$5500,$A15,Data!$J$2:$J$5500,$B15) -> 1533224864 | G15: =SUMIFS(Data!$Q$2:$Q$5500,Data!$I$2:$I$5500,$A15,Data!$J$2:$J$5500,$B15) -> 404721740 | H15: =IFERROR(G15/D15,0) -> 0.22192086 | I15: =IFERROR(G15/C15,0) -> 2248454.1 | J15: =RANK(G15,$G$13:$G$29) -> 3
A16: Technology | B16: Telephones & Communication | C16: =COUNTIFS(Data!$I$2:$I$5500,$A16,Data!$J$2:$J$5500,$B16,Data!$L$2:$L$5500,1)+COUNTIFS(Data!$I$2:$I$5500,$A16,Data!$J$2:$J$5500,$B16,Data!$M$2:$M$5500,1) -> 429 | D16: =SUMIFS(Data!$F$2:$F$5500,Data!$I$2:$I$5500,$A16,Data!$J$2:$J$5500,$B16,Data!$L$2:$L$5500,1)+SUMIFS(Data!$F$2:$F$5500,Data!$I$2:$I$5500,$A16,Data!$J$2:$J$5500,$B16,Data!$M$2:$M$5500,1) -> 1759096403 | E16: =IFERROR(SUMIFS(Data!$F$2:$F$5500,Data!$I$2:$I$5500,$A16,Data!$J$2:$J$5500,$B16,Data!$M$2:$M$5500,1)/D16,0) -> 0.094788535 | F16: =SUMIFS(Data!$P$2:$P$5500,Data!$I$2:$I$5500,$A16,Data!$J$2:$J$5500,$B16) -> 1512787907 | G16: =SUMIFS(Data!$Q$2:$Q$5500,Data!$I$2:$I$5500,$A16,Data!$J$2:$J$5500,$B16) -> 3.9813994e+08 | H16: =IFERROR(G16/D16,0) -> 0.22633208 | I16: =IFERROR(G16/C16,0) -> 928065.14 | J16: =RANK(G16,$G$13:$G$29) -> 4
A17: Office Supplies | B17: Binders & Binder Accessories | C17: =COUNTIFS(Data!$I$2:$I$5500,$A17,Data!$J$2:$J$5500,$B17,Data!$L$2:$L$5500,1)+COUNTIFS(Data!$I$2:$I$5500,$A17,Data!$J$2:$J$5500,$B17,Data!$M$2:$M$5500,1) -> 765 | D17: =SUMIFS(Data!$F$2:$F$5500,Data!$I$2:$I$5500,$A17,Data!$J$2:$J$5500,$B17,Data!$L$2:$L$5500,1)+SUMIFS(Data!$F$2:$F$5500,Data!$I$2:$I$5500,$A17,Data!$J$2:$J$5500,$B17,Data!$M$2:$M$5500,1) -> 1645264680 | E17: =IFERROR(SUMIFS(Data!$F$2:$F$5500,Data!$I$2:$I$5500,$A17,Data!$J$2:$J$5500,$B17,Data!$M$2:$M$5500,1)/D17,0) -> 0.19635547 | F17: =SUMIFS(Data!$P$2:$P$5500,Data!$I$2:$I$5500,$A17,Data!$J$2:$J$5500,$B17) -> 1250652221 | G17: =SUMIFS(Data!$Q$2:$Q$5500,Data!$I$2:$I$5500,$A17,Data!$J$2:$J$5500,$B17) -> 325106649 | H17: =IFERROR(G17/D17,0) -> 0.19760143 | I17: =IFERROR(G17/C17,0) -> 424976.01 | J17: =RANK(G17,$G$13:$G$29) -> 5
A18: Technology | B18: Copiers & Fax | C18: =COUNTIFS(Data!$I$2:$I$5500,$A18,Data!$J$2:$J$5500,$B18,Data!$L$2:$L$5500,1)+COUNTIFS(Data!$I$2:$I$5500,$A18,Data!$J$2:$J$5500,$B18,Data!$M$2:$M$5500,1) -> 56 | D18: =SUMIFS(Data!$F$2:$F$5500,Data!$I$2:$I$5500,$A18,Data!$J$2:$J$5500,$B18,Data!$L$2:$L$5500,1)+SUMIFS(Data!$F$2:$F$5500,Data!$I$2:$I$5500,$A18,Data!$J$2:$J$5500,$B18,Data!$M$2:$M$5500,1) -> 1469965760 | E18: =IFERROR(SUMIFS(Data!$F$2:$F$5500,Data!$I$2:$I$5500,$A18,Data!$J$2:$J$5500,$B18,Data!$M$2:$M$5500,1)/D18,0) -> 0.14869931 | F18: =SUMIFS(Data!$P$2:$P$5500,Data!$I$2:$I$5500,$A18,Data!$J$2:$J$5500,$B18) -> 1178760231 | G18: =SUMIFS(Data!$Q$2:$Q$5500,Data!$I$2:$I$5500,$A18,Data!$J$2:$J$5500,$B18) -> 302792229 | H18: =IFERROR(G18/D18,0) -> 0.20598591 | I18: =IFERROR(G18/C18,0) -> 5407004.1 | J18: =RANK(G18,$G$13:$G$29) -> 6
A19: Office Supplies | B19: Storage & Organization | C19: =COUNTIFS(Data!$I$2:$I$5500,$A19,Data!$J$2:$J$5500,$B19,Data!$L$2:$L$5500,1)+COUNTIFS(Data!$I$2:$I$5500,$A19,Data!$J$2:$J$5500,$B19,Data!$M$2:$M$5500,1) -> 276 | D19: =SUMIFS(Data!$F$2:$F$5500,Data!$I$2:$I$5500,$A19,Data!$J$2:$J$5500,$B19,Data!$L$2:$L$5500,1)+SUMIFS(Data!$F$2:$F$5500,Data!$I$2:$I$5500,$A19,Data!$J$2:$J$5500,$B19,Data!$M$2:$M$5500,1) -> 1317117740 | E19: =IFERROR(SUMIFS(Data!$F$2:$F$5500,Data!$I$2:$I$5500,$A19,Data!$J$2:$J$5500,$B19,Data!$M$2:$M$5500,1)/D19,0) -> 0.086080307 | F19: =SUMIFS(Data!$P$2:$P$5500,Data!$I$2:$I$5500,$A19,Data!$J$2:$J$5500,$B19) -> 1144054266 | G19: =SUMIFS(Data!$Q$2:$Q$5500,Data!$I$2:$I$5500,$A19,Data!$J$2:$J$5500,$B19) -> 301436378 | H19: =IFERROR(G19/D19,0) -> 0.22886062 | I19: =IFERROR(G19/C19,0) -> 1092160.8 | J19: =RANK(G19,$G$13:$G$29) -> 7
A20: Office Supplies | B20: Appliances | C20: =COUNTIFS(Data!$I$2:$I$5500,$A20,Data!$J$2:$J$5500,$B20,Data!$L$2:$L$5500,1)+COUNTIFS(Data!$I$2:$I$5500,$A20,Data!$J$2:$J$5500,$B20,Data!$M$2:$M$5500,1) -> 375 | D20: =SUMIFS(Data!$F$2:$F$5500,Data!$I$2:$I$5500,$A20,Data!$J$2:$J$5500,$B20,Data!$L$2:$L$5500,1)+SUMIFS(Data!$F$2:$F$5500,Data!$I$2:$I$5500,$A20,Data!$J$2:$J$5500,$B20,Data!$M$2:$M$5500,1) -> 1238552900 | E20: =IFERROR(SUMIFS(Data!$F$2:$F$5500,Data!$I$2:$I$5500,$A20,Data!$J$2:$J$5500,$B20,Data!$M$2:$M$5500,1)/D20,0) -> 0.060004542 | F20: =SUMIFS(Data!$P$2:$P$5500,Data!$I$2:$I$5500,$A20,Data!$J$2:$J$5500,$B20) -> 1101923304 | G20: =SUMIFS(Data!$Q$2:$Q$5500,Data!$I$2:$I$5500,$A20,Data!$J$2:$J$5500,$B20) -> 286959434 | H20: =IFERROR(G20/D20,0) -> 0.23168928 | I20: =IFERROR(G20/C20,0) -> 765225.16 | J20: =RANK(G20,$G$13:$G$29) -> 8
A21: Technology | B21: Computer Peripherals | C21: =COUNTIFS(Data!$I$2:$I$5500,$A21,Data!$J$2:$J$5500,$B21,Data!$L$2:$L$5500,1)+COUNTIFS(Data!$I$2:$I$5500,$A21,Data!$J$2:$J$5500,$B21,Data!$M$2:$M$5500,1) -> 561 | D21: =SUMIFS(Data!$F$2:$F$5500,Data!$I$2:$I$5500,$A21,Data!$J$2:$J$5500,$B21,Data!$L$2:$L$5500,1)+SUMIFS(Data!$F$2:$F$5500,Data!$I$2:$I$5500,$A21,Data!$J$2:$J$5500,$B21,Data!$M$2:$M$5500,1) -> 1201653980 | E21: =IFERROR(SUMIFS(Data!$F$2:$F$5500,Data!$I$2:$I$5500,$A21,Data!$J$2:$J$5500,$B21,Data!$M$2:$M$5500,1)/D21,0) -> 0.09217269 | F21: =SUMIFS(Data!$P$2:$P$5500,Data!$I$2:$I$5500,$A21,Data!$J$2:$J$5500,$B21) -> 1035677142 | G21: =SUMIFS(Data!$Q$2:$Q$5500,Data!$I$2:$I$5500,$A21,Data!$J$2:$J$5500,$B21) -> 272051132 | H21: =IFERROR(G21/D21,0) -> 0.22639723 | I21: =IFERROR(G21/C21,0) -> 484939.63 | J21: =RANK(G21,$G$13:$G$29) -> 9
A22: Furniture | B22: Bookcases | C22: =COUNTIFS(Data!$I$2:$I$5500,$A22,Data!$J$2:$J$5500,$B22,Data!$L$2:$L$5500,1)+COUNTIFS(Data!$I$2:$I$5500,$A22,Data!$J$2:$J$5500,$B22,Data!$M$2:$M$5500,1) -> 142 | D22: =SUMIFS(Data!$F$2:$F$5500,Data!$I$2:$I$5500,$A22,Data!$J$2:$J$5500,$B22,Data!$L$2:$L$5500,1)+SUMIFS(Data!$F$2:$F$5500,Data!$I$2:$I$5500,$A22,Data!$J$2:$J$5500,$B22,Data!$M$2:$M$5500,1) -> 1148115720 | E22: =IFERROR(SUMIFS(Data!$F$2:$F$5500,Data!$I$2:$I$5500,$A22,Data!$J$2:$J$5500,$B22,Data!$M$2:$M$5500,1)/D22,0) -> 0.14804718 | F22: =SUMIFS(Data!$P$2:$P$5500,Data!$I$2:$I$5500,$A22,Data!$J$2:$J$5500,$B22) -> 941319471 | G22: =SUMIFS(Data!$Q$2:$Q$5500,Data!$I$2:$I$5500,$A22,Data!$J$2:$J$5500,$B22) -> 256621177 | H22: =IFERROR(G22/D22,0) -> 0.22351508 | I22: =IFERROR(G22/C22,0) -> 1807191.4 | J22: =RANK(G22,$G$13:$G$29) -> 10
A23: Furniture | B23: Office Furnishings | C23: =COUNTIFS(Data!$I$2:$I$5500,$A23,Data!$J$2:$J$5500,$B23,Data!$L$2:$L$5500,1)+COUNTIFS(Data!$I$2:$I$5500,$A23,Data!$J$2:$J$5500,$B23,Data!$M$2:$M$5500,1) -> 530 | D23: =SUMIFS(Data!$F$2:$F$5500,Data!$I$2:$I$5500,$A23,Data!$J$2:$J$5500,$B23,Data!$L$2:$L$5500,1)+SUMIFS(Data!$F$2:$F$5500,Data!$I$2:$I$5500,$A23,Data!$J$2:$J$5500,$B23,Data!$M$2:$M$5500,1) -> 887191060 | E23: =IFERROR(SUMIFS(Data!$F$2:$F$5500,Data!$I$2:$I$5500,$A23,Data!$J$2:$J$5500,$B23,Data!$M$2:$M$5500,1)/D23,0) -> 0.13358611 | F23: =SUMIFS(Data!$P$2:$P$5500,Data!$I$2:$I$5500,$A23,Data!$J$2:$J$5500,$B23) -> 731320533 | G23: =SUMIFS(Data!$Q$2:$Q$5500,Data!$I$2:$I$5500,$A23,Data!$J$2:$J$5500,$B23) -> 193248271 | H23: =IFERROR(G23/D23,0) -> 0.21782035 | I23: =IFERROR(G23/C23,0) -> 364619.38 | J23: =RANK(G23,$G$13:$G$29) -> 11
A24: Office Supplies | B24: Paper | C24: =COUNTIFS(Data!$I$2:$I$5500,$A24,Data!$J$2:$J$5500,$B24,Data!$L$2:$L$5500,1)+COUNTIFS(Data!$I$2:$I$5500,$A24,Data!$J$2:$J$5500,$B24,Data!$M$2:$M$5500,1) -> 736 | D24: =SUMIFS(Data!$F$2:$F$5500,Data!$I$2:$I$5500,$A24,Data!$J$2:$J$5500,$B24,Data!$L$2:$L$5500,1)+SUMIFS(Data!$F$2:$F$5500,Data!$I$2:$I$5500,$A24,Data!$J$2:$J$5500,$B24,Data!$M$2:$M$5500,1) -> 515461960 | E24: =IFERROR(SUMIFS(Data!$F$2:$F$5500,Data!$I$2:$I$5500,$A24,Data!$J$2:$J$5500,$B24,Data!$M$2:$M$5500,1)/D24,0) -> 0.089928227 | F24: =SUMIFS(Data!$P$2:$P$5500,Data!$I$2:$I$5500,$A24,Data!$J$2:$J$5500,$B24) -> 446724894 | G24: =SUMIFS(Data!$Q$2:$Q$5500,Data!$I$2:$I$5500,$A24,Data!$J$2:$J$5500,$B24) -> 118349728 | H24: =IFERROR(G24/D24,0) -> 0.22959934 | I24: =IFERROR(G24/C24,0) -> 160801.26 | J24: =RANK(G24,$G$13:$G$29) -> 12
... A29: Office Supplies | B29: Rubber Bands | C29: =COUNTIFS(Data!$I$2:$I$5500,$A29,Data!$J$2:$J$5500,$B29,Data!$L$2:$L$5500,1)+COUNTIFS(Data!$I$2:$I$5500,$A29,Data!$J$2:$J$5500,$B29,Data!$M$2:$M$5500,1) -> 97 | D29: =SUMIFS(Data!$F$2:$F$5500,Data!$I$2:$I$5500,$A29,Data!$J$2:$J$5500,$B29,Data!$L$2:$L$5500,1)+SUMIFS(Data!$F$2:$F$5500,Data!$I$2:$I$5500,$A29,Data!$J$2:$J$5500,$B29,Data!$M$2:$M$5500,1) -> 16333880 | E29: =IFERROR(SUMIFS(Data!$F$2:$F$5500,Data!$I$2:$I$5500,$A29,Data!$J$2:$J$5500,$B29,Data!$M$2:$M$5500,1)/D29,0) -> 0.18189432 | F29: =SUMIFS(Data!$P$2:$P$5500,Data!$I$2:$I$5500,$A29,Data!$J$2:$J$5500,$B29) -> 12706959 | G29: =SUMIFS(Data!$Q$2:$Q$5500,Data!$I$2:$I$5500,$A29,Data!$J$2:$J$5500,$B29) -> 3352971 | H29: =IFERROR(G29/D29,0) -> 0.20527707 | I29: =IFERROR(G29/C29,0) -> 34566.711 | J29: =RANK(G29,$G$13:$G$29) -> 17
A32: 3. Tren Net Revenue per tahun (Rp juta)
A33: Tahun | B33: Furniture | C33: Office Supplies | D33: Technology | E33: Total
A34: 2009 | B34: =SUMIFS(Data!$P$2:$P$5500,Data!$K$2:$K$5500,$A34,Data!$I$2:$I$5500,B$33) -> 1666031409 | C34: =SUMIFS(Data!$P$2:$P$5500,Data!$K$2:$K$5500,$A34,Data!$I$2:$I$5500,C$33) -> 1167133407 | D34: =SUMIFS(Data!$P$2:$P$5500,Data!$K$2:$K$5500,$A34,Data!$I$2:$I$5500,D$33) -> 1566377538 | E34: =SUM(B34:D34) -> 4399542354
A35: 2010 | B35: =SUMIFS(Data!$P$2:$P$5500,Data!$K$2:$K$5500,$A35,Data!$I$2:$I$5500,B$33) -> 1290937396 | C35: =SUMIFS(Data!$P$2:$P$5500,Data!$K$2:$K$5500,$A35,Data!$I$2:$I$5500,C$33) -> 1057498902 | D35: =SUMIFS(Data!$P$2:$P$5500,Data!$K$2:$K$5500,$A35,Data!$I$2:$I$5500,D$33) -> 1513157370 | E35: =SUM(B35:D35) -> 3861593668
A36: 2011 | B36: =SUMIFS(Data!$P$2:$P$5500,Data!$K$2:$K$5500,$A36,Data!$I$2:$I$5500,B$33) -> 1389367236 | C36: =SUMIFS(Data!$P$2:$P$5500,Data!$K$2:$K$5500,$A36,Data!$I$2:$I$5500,C$33) -> 1022330753 | D36: =SUMIFS(Data!$P$2:$P$5500,Data!$K$2:$K$5500,$A36,Data!$I$2:$I$5500,D$33) -> 1485726641 | E36: =SUM(B36:D36) -> 3897424630
A37: 2012 | B37: =SUMIFS(Data!$P$2:$P$5500,Data!$K$2:$K$5500,$A37,Data!$I$2:$I$5500,B$33) -> 1320843899 | C37: =SUMIFS(Data!$P$2:$P$5500,Data!$K$2:$K$5500,$A37,Data!$I$2:$I$5500,C$33) -> 1197333869 | D37: =SUMIFS(Data!$P$2:$P$5500,Data!$K$2:$K$5500,$A37,Data!$I$2:$I$5500,D$33) -> 1738937748 | E37: =SUM(B37:D37) -> 4257115516

Sheet Diskon
A1: Analisis Diskon: Efektivitas & Sensitivitas
A2: Bucket diskon: A=0%, B=1–3%, C=4–6%, D=7%+ (termasuk 3 order Furniture >10%). Hanya order valid (Finished+Returned).
A4: 1. Jumlah order per bucket diskon
A5: Kategori | B5: A: 0% | C5: B: 1-3% | D5: C: 4-6% | E5: D: 7%+
A6: Furniture | B6: =COUNTIFS(Data!$I$2:$I$5500,$A6,Data!$O$2:$O$5500,B$5,Data!$N$2:$N$5500,1) -> 107 | C6: =COUNTIFS(Data!$I$2:$I$5500,$A6,Data!$O$2:$O$5500,C$5,Data!$N$2:$N$5500,1) -> 324 | D6: =COUNTIFS(Data!$I$2:$I$5500,$A6,Data!$O$2:$O$5500,D$5,Data!$N$2:$N$5500,1) -> 307 | E6: =COUNTIFS(Data!$I$2:$I$5500,$A6,Data!$O$2:$O$5500,E$5,Data!$N$2:$N$5500,1) -> 415
A7: Office Supplies | B7: =COUNTIFS(Data!$I$2:$I$5500,$A7,Data!$O$2:$O$5500,B$5,Data!$N$2:$N$5500,1) -> 267 | C7: =COUNTIFS(Data!$I$2:$I$5500,$A7,Data!$O$2:$O$5500,C$5,Data!$N$2:$N$5500,1) -> 855 | D7: =COUNTIFS(Data!$I$2:$I$5500,$A7,Data!$O$2:$O$5500,D$5,Data!$N$2:$N$5500,1) -> 815 | E7: =COUNTIFS(Data!$I$2:$I$5500,$A7,Data!$O$2:$O$5500,E$5,Data!$N$2:$N$5500,1) -> 1126
A8: Technology | B8: =COUNTIFS(Data!$I$2:$I$5500,$A8,Data!$O$2:$O$5500,B$5,Data!$N$2:$N$5500,1) -> 136 | C8: =COUNTIFS(Data!$I$2:$I$5500,$A8,Data!$O$2:$O$5500,C$5,Data!$N$2:$N$5500,1) -> 320 | D8: =COUNTIFS(Data!$I$2:$I$5500,$A8,Data!$O$2:$O$5500,D$5,Data!$N$2:$N$5500,1) -> 374 | E8: =COUNTIFS(Data!$I$2:$I$5500,$A8,Data!$O$2:$O$5500,E$5,Data!$N$2:$N$5500,1) -> 450
A11: 2. Rata-rata qty per order per bucket diskon
A12: Kategori | B12: A: 0% | C12: B: 1-3% | D12: C: 4-6% | E12: D: 7%+ | F12: Lift qty (7%+ vs 0%)
A13: Furniture | B13: =AVERAGEIFS(Data!$E$2:$E$5500,Data!$I$2:$I$5500,$A13,Data!$O$2:$O$5500,B$12,Data!$N$2:$N$5500,1) -> 28.242991 | C13: =AVERAGEIFS(Data!$E$2:$E$5500,Data!$I$2:$I$5500,$A13,Data!$O$2:$O$5500,C$12,Data!$N$2:$N$5500,1) -> 25.37037 | D13: =AVERAGEIFS(Data!$E$2:$E$5500,Data!$I$2:$I$5500,$A13,Data!$O$2:$O$5500,D$12,Data!$N$2:$N$5500,1) -> 24.332248 | E13: =AVERAGEIFS(Data!$E$2:$E$5500,Data!$I$2:$I$5500,$A13,Data!$O$2:$O$5500,E$12,Data!$N$2:$N$5500,1) -> 25.537349 | F13: =E13/B13-1 -> -0.095798681
A14: Office Supplies | B14: =AVERAGEIFS(Data!$E$2:$E$5500,Data!$I$2:$I$5500,$A14,Data!$O$2:$O$5500,B$12,Data!$N$2:$N$5500,1) -> 25.741573 | C14: =AVERAGEIFS(Data!$E$2:$E$5500,Data!$I$2:$I$5500,$A14,Data!$O$2:$O$5500,C$12,Data!$N$2:$N$5500,1) -> 25.45731 | D14: =AVERAGEIFS(Data!$E$2:$E$5500,Data!$I$2:$I$5500,$A14,Data!$O$2:$O$5500,D$12,Data!$N$2:$N$5500,1) -> 25.211043 | E14: =AVERAGEIFS(Data!$E$2:$E$5500,Data!$I$2:$I$5500,$A14,Data!$O$2:$O$5500,E$12,Data!$N$2:$N$5500,1) -> 25.877442 | F14: =E14/B14-1 -> 0.0052782027
A15: Technology | B15: =AVERAGEIFS(Data!$E$2:$E$5500,Data!$I$2:$I$5500,$A15,Data!$O$2:$O$5500,B$12,Data!$N$2:$N$5500,1) -> 26.161765 | C15: =AVERAGEIFS(Data!$E$2:$E$5500,Data!$I$2:$I$5500,$A15,Data!$O$2:$O$5500,C$12,Data!$N$2:$N$5500,1) -> 26.021875 | D15: =AVERAGEIFS(Data!$E$2:$E$5500,Data!$I$2:$I$5500,$A15,Data!$O$2:$O$5500,D$12,Data!$N$2:$N$5500,1) -> 24.628342 | E15: =AVERAGEIFS(Data!$E$2:$E$5500,Data!$I$2:$I$5500,$A15,Data!$O$2:$O$5500,E$12,Data!$N$2:$N$5500,1) -> 25.588889 | F15: =E15/B15-1 -> -0.021897446
A18: 3. Rata-rata sales per order per bucket diskon (Rp juta)
A19: Kategori | B19: A: 0% | C19: B: 1-3% | D19: C: 4-6% | E19: D: 7%+ | F19: Lift sales/order (7%+ vs 0%)
A20: Furniture | B20: =AVERAGEIFS(Data!$F$2:$F$5500,Data!$I$2:$I$5500,$A20,Data!$O$2:$O$5500,B$19,Data!$N$2:$N$5500,1) -> 5392020.9 | C20: =AVERAGEIFS(Data!$F$2:$F$5500,Data!$I$2:$I$5500,$A20,Data!$O$2:$O$5500,C$19,Data!$N$2:$N$5500,1) -> 6786071.9 | D20: =AVERAGEIFS(Data!$F$2:$F$5500,Data!$I$2:$I$5500,$A20,Data!$O$2:$O$5500,D$19,Data!$N$2:$N$5500,1) -> 5376026.6 | E20: =AVERAGEIFS(Data!$F$2:$F$5500,Data!$I$2:$I$5500,$A20,Data!$O$2:$O$5500,E$19,Data!$N$2:$N$5500,1) -> 5372717.8 | F20: =E20/B20-1 -> -0.0035799367
A21: Office Supplies | B21: =AVERAGEIFS(Data!$F$2:$F$5500,Data!$I$2:$I$5500,$A21,Data!$O$2:$O$5500,B$19,Data!$N$2:$N$5500,1) -> 1748880.4 | C21: =AVERAGEIFS(Data!$F$2:$F$5500,Data!$I$2:$I$5500,$A21,Data!$O$2:$O$5500,C$19,Data!$N$2:$N$5500,1) -> 1743192.9 | D21: =AVERAGEIFS(Data!$F$2:$F$5500,Data!$I$2:$I$5500,$A21,Data!$O$2:$O$5500,D$19,Data!$N$2:$N$5500,1) -> 1617720 | E21: =AVERAGEIFS(Data!$F$2:$F$5500,Data!$I$2:$I$5500,$A21,Data!$O$2:$O$5500,E$19,Data!$N$2:$N$5500,1) -> 1806001.8 | F21: =E21/B21-1 -> 0.032661718
A22: Technology | B22: =AVERAGEIFS(Data!$F$2:$F$5500,Data!$I$2:$I$5500,$A22,Data!$O$2:$O$5500,B$19,Data!$N$2:$N$5500,1) -> 7018954.4 | C22: =AVERAGEIFS(Data!$F$2:$F$5500,Data!$I$2:$I$5500,$A22,Data!$O$2:$O$5500,C$19,Data!$N$2:$N$5500,1) -> 4889168.8 | D22: =AVERAGEIFS(Data!$F$2:$F$5500,Data!$I$2:$I$5500,$A22,Data!$O$2:$O$5500,D$19,Data!$N$2:$N$5500,1) -> 5997368.1 | E22: =AVERAGEIFS(Data!$F$2:$F$5500,Data!$I$2:$I$5500,$A22,Data!$O$2:$O$5500,E$19,Data!$N$2:$N$5500,1) -> 5912514.1 | F22: =E22/B22-1 -> -0.15763605
A25: 4. Return rate (by jumlah order) per bucket diskon
A26: Kategori | B26: A: 0% | C26: B: 1-3% | D26: C: 4-6% | E26: D: 7%+ | F26: Δ return (7%+ − 0%)
A27: Furniture | B27: =COUNTIFS(Data!$I$2:$I$5500,$A27,Data!$O$2:$O$5500,B$26,Data!$M$2:$M$5500,1)/COUNTIFS(Data!$I$2:$I$5500,$A27,Data!$O$2:$O$5500,B$26,Data!$N$2:$N$5500,1) -> 0.11214953 | C27: =COUNTIFS(Data!$I$2:$I$5500,$A27,Data!$O$2:$O$5500,C$26,Data!$M$2:$M$5500,1)/COUNTIFS(Data!$I$2:$I$5500,$A27,Data!$O$2:$O$5500,C$26,Data!$N$2:$N$5500,1) -> 0.11111111 | D27: =COUNTIFS(Data!$I$2:$I$5500,$A27,Data!$O$2:$O$5500,D$26,Data!$M$2:$M$5500,1)/COUNTIFS(Data!$I$2:$I$5500,$A27,Data!$O$2:$O$5500,D$26,Data!$N$2:$N$5500,1) -> 0.094462541 | E27: =COUNTIFS(Data!$I$2:$I$5500,$A27,Data!$O$2:$O$5500,E$26,Data!$M$2:$M$5500,1)/COUNTIFS(Data!$I$2:$I$5500,$A27,Data!$O$2:$O$5500,E$26,Data!$N$2:$N$5500,1) -> 0.11807229 | F27: =E27-B27 -> 0.0059227564
A28: Office Supplies | B28: =COUNTIFS(Data!$I$2:$I$5500,$A28,Data!$O$2:$O$5500,B$26,Data!$M$2:$M$5500,1)/COUNTIFS(Data!$I$2:$I$5500,$A28,Data!$O$2:$O$5500,B$26,Data!$N$2:$N$5500,1) -> 0.13483146 | C28: =COUNTIFS(Data!$I$2:$I$5500,$A28,Data!$O$2:$O$5500,C$26,Data!$M$2:$M$5500,1)/COUNTIFS(Data!$I$2:$I$5500,$A28,Data!$O$2:$O$5500,C$26,Data!$N$2:$N$5500,1) -> 0.10526316 | D28: =COUNTIFS(Data!$I$2:$I$5500,$A28,Data!$O$2:$O$5500,D$26,Data!$M$2:$M$5500,1)/COUNTIFS(Data!$I$2:$I$5500,$A28,Data!$O$2:$O$5500,D$26,Data!$N$2:$N$5500,1) -> 0.10306748 | E28: =COUNTIFS(Data!$I$2:$I$5500,$A28,Data!$O$2:$O$5500,E$26,Data!$M$2:$M$5500,1)/COUNTIFS(Data!$I$2:$I$5500,$A28,Data!$O$2:$O$5500,E$26,Data!$N$2:$N$5500,1) -> 0.086145648 | F28: =E28-B28 -> -0.048685812
A29: Technology | B29: =COUNTIFS(Data!$I$2:$I$5500,$A29,Data!$O$2:$O$5500,B$26,Data!$M$2:$M$5500,1)/COUNTIFS(Data!$I$2:$I$5500,$A29,Data!$O$2:$O$5500,B$26,Data!$N$2:$N$5500,1) -> 0.125 | C29: =COUNTIFS(Data!$I$2:$I$5500,$A29,Data!$O$2:$O$5500,C$26,Data!$M$2:$M$5500,1)/COUNTIFS(Data!$I$2:$I$5500,$A29,Data!$O$2:$O$5500,C$26,Data!$N$2:$N$5500,1) -> 0.128125 | D29: =COUNTIFS(Data!$I$2:$I$5500,$A29,Data!$O$2:$O$5500,D$26,Data!$M$2:$M$5500,1)/COUNTIFS(Data!$I$2:$I$5500,$A29,Data!$O$2:$O$5500,D$26,Data!$N$2:$N$5500,1) -> 0.11497326 | E29: =COUNTIFS(Data!$I$2:$I$5500,$A29,Data!$O$2:$O$5500,E$26,Data!$M$2:$M$5500,1)/COUNTIFS(Data!$I$2:$I$5500,$A29,Data!$O$2:$O$5500,E$26,Data!$N$2:$N$5500,1) -> 0.084444444 | F29: =E29-B29 -> -0.040555556
A32: 5. Korelasi Pearson (diskon vs qty & sales per order) – dihitung manual dengan SUMPRODUCT
A33: Kategori | B33: n | C33: Σ disc | D33: Σ disc² | E33: Σ qty | F33: Σ qty² | G33: Σ disc·qty | H33: Σ sales | I33: Σ sales² | J33: Σ disc·sales | K33: r (disc, qty) | L33: r (disc, sales/order) | M33: Kesimpulan
A34: Furniture | B34: =SUMPRODUCT((Data!$I$2:$I$5500=$A34)*(Data!$N$2:$N$5500=1)) -> 1153 | C34: =SUMPRODUCT((Data!$I$2:$I$5500=$A34)*(Data!$N$2:$N$5500=1)*Data!$G$2:$G$5500) -> 56.99 | D34: =SUMPRODUCT((Data!$I$2:$I$5500=$A34)*(Data!$N$2:$N$5500=1)*Data!$G$2:$G$5500^2) -> 4.0063 | E34: =SUMPRODUCT((Data!$I$2:$I$5500=$A34)*(Data!$N$2:$N$5500=1)*Data!$E$2:$E$5500) -> 29310 | F34: =SUMPRODUCT((Data!$I$2:$I$5500=$A34)*(Data!$N$2:$N$5500=1)*Data!$E$2:$E$5500^2) -> 996516 | G34: =SUMPRODUCT((Data!$I$2:$I$5500=$A34)*(Data!$N$2:$N$5500=1)*Data!$G$2:$G$5500*Data!$E$2:$E$5500) -> 1433.27 | H34: =SUMPRODUCT((Data!$I$2:$I$5500=$A34)*(Data!$N$2:$N$5500=1)*Data!$F$2:$F$5500) -> 6655751588 | I34: =SUMPRODUCT((Data!$I$2:$I$5500=$A34)*(Data!$N$2:$N$5500=1)*Data!$F$2:$F$5500^2) -> 1.0887597e+17 | J34: =SUMPRODUCT((Data!$I$2:$I$5500=$A34)*(Data!$N$2:$N$5500=1)*Data!$G$2:$G$5500*Data!$F$2:$F$5500) -> 3.118992e+08 | K34: =(B34*G34-C34*E34)/SQRT((B34*D34-C34^2)*(B34*F34-E34^2)) -> -0.02825613 | L34: =(B34*J34-C34*H34)/SQRT((B34*D34-C34^2)*(B34*I34-H34^2)) -> -0.058996309 | M34: =IF(MAX(ABS(K34),ABS(L34))<Asumsi!$B$11,"Tidak sensitif","Sensitif") -> Tidak sensitif
A35: Office Supplies | B35: =SUMPRODUCT((Data!$I$2:$I$5500=$A35)*(Data!$N$2:$N$5500=1)) -> 3063 | C35: =SUMPRODUCT((Data!$I$2:$I$5500=$A35)*(Data!$N$2:$N$5500=1)*Data!$G$2:$G$5500) -> 153.89 | D35: =SUMPRODUCT((Data!$I$2:$I$5500=$A35)*(Data!$N$2:$N$5500=1)*Data!$G$2:$G$5500^2) -> 10.7951 | E35: =SUMPRODUCT((Data!$I$2:$I$5500=$A35)*(Data!$N$2:$N$5500=1)*Data!$E$2:$E$5500) -> 78324 | F35: =SUMPRODUCT((Data!$I$2:$I$5500=$A35)*(Data!$N$2:$N$5500=1)*Data!$E$2:$E$5500^2) -> 2630420 | G35: =SUMPRODUCT((Data!$I$2:$I$5500=$A35)*(Data!$N$2:$N$5500=1)*Data!$G$2:$G$5500*Data!$E$2:$E$5500) -> 3925.91 | H35: =SUMPRODUCT((Data!$I$2:$I$5500=$A35)*(Data!$N$2:$N$5500=1)*Data!$F$2:$F$5500) -> 5309380840 | I35: =SUMPRODUCT((Data!$I$2:$I$5500=$A35)*(Data!$N$2:$N$5500=1)*Data!$F$2:$F$5500^2) -> 6.6397082e+16 | J35: =SUMPRODUCT((Data!$I$2:$I$5500=$A35)*(Data!$N$2:$N$5500=1)*Data!$G$2:$G$5500*Data!$F$2:$F$5500) -> 2.681626e+08 | K35: =(B35*G35-C35*E35)/SQRT((B35*D35-C35^2)*(B35*F35-E35^2)) -> -0.0066440998 | L35: =(B35*J35-C35*H35)/SQRT((B35*D35-C35^2)*(B35*I35-H35^2)) -> 0.0033705514 | M35: =IF(MAX(ABS(K35),ABS(L35))<Asumsi!$B$11,"Tidak sensitif","Sensitif") -> Tidak sensitif
A36: Technology | B36: =SUMPRODUCT((Data!$I$2:$I$5500=$A36)*(Data!$N$2:$N$5500=1)) -> 1280 | C36: =SUMPRODUCT((Data!$I$2:$I$5500=$A36)*(Data!$N$2:$N$5500=1)*Data!$G$2:$G$5500) -> 63.4 | D36: =SUMPRODUCT((Data!$I$2:$I$5500=$A36)*(Data!$N$2:$N$5500=1)*Data!$G$2:$G$5500^2) -> 4.438 | E36: =SUMPRODUCT((Data!$I$2:$I$5500=$A36)*(Data!$N$2:$N$5500=1)*Data!$E$2:$E$5500) -> 32611 | F36: =SUMPRODUCT((Data!$I$2:$I$5500=$A36)*(Data!$N$2:$N$5500=1)*Data!$E$2:$E$5500^2) -> 1103929 | G36: =SUMPRODUCT((Data!$I$2:$I$5500=$A36)*(Data!$N$2:$N$5500=1)*Data!$G$2:$G$5500*Data!$E$2:$E$5500) -> 1607.52 | H36: =SUMPRODUCT((Data!$I$2:$I$5500=$A36)*(Data!$N$2:$N$5500=1)*Data!$F$2:$F$5500) -> 7422758843 | I36: =SUMPRODUCT((Data!$I$2:$I$5500=$A36)*(Data!$N$2:$N$5500=1)*Data!$F$2:$F$5500^2) -> 1.8526515e+17 | J36: =SUMPRODUCT((Data!$I$2:$I$5500=$A36)*(Data!$N$2:$N$5500=1)*Data!$G$2:$G$5500*Data!$F$2:$F$5500) -> 3.7205688e+08 | K36: =(B36*G36-C36*E36)/SQRT((B36*D36-C36^2)*(B36*F36-E36^2)) -> -0.013007729 | L36: =(B36*J36-C36*H36)/SQRT((B36*D36-C36^2)*(B36*I36-H36^2)) -> 0.010238092 | M36: =IF(MAX(ABS(K36),ABS(L36))<Asumsi!$B$11,"Tidak sensitif","Sensitif") -> Tidak sensitif
A38: 6. Biaya diskon (Order Finished)
A39: Kategori | B39: Diskon Diberikan (Rp juta) | C39: % dari Sales | D39: Gross Profit sebelum Diskon (Rp juta) | E39: Diskon sebagai % Gross Profit
A40: Furniture | B40: =Kategori!F5 -> 273303320 | C40: =Kategori!G5 -> 0.046006917 | D40: =Kategori!I5+Kategori!F5 -> 1782144978 | E40: =B40/D40 -> 0.15335639
A41: Office Supplies | B41: =Kategori!F6 -> 241274489 | C41: =Kategori!G6 -> 0.051493077 | D41: =Kategori!I6+Kategori!F6 -> 1405671426 | E41: =B41/D41 -> 0.17164359
A42: Technology | B42: =Kategori!F7 -> 337738655 | C42: =Kategori!G7 -> 0.050849414 | D42: =Kategori!I7+Kategori!F7 -> 1.9925814e+09 | E42: =B42/D42 -> 0.16949805
A43: Total | B43: =SUM(B40:B42) -> 852316464 | C43: =Kategori!G8 -> 0.049358167 | D43: =SUM(D40:D42) -> 5.1803978e+09 | E43: =B43/D43 -> 0.16452722
A45: Catatan: korelasi & lift bersifat observasional. Karena diskon tersebar hampir merata 0–10% di semua kategori (±500 order per level), data ini mendekati "eksperimen alami", tetapi tetap bukan A/B test.

Sheet Data
A1: order_id | B1: order_status | C1: customer | D1: order_date | E1: order_quantity | F1: sales | G1: discount | H1: discount_value | I1: product_category | J1: product_sub_category | K1: year | L1: is_finished | M1: is_returned | N1: is_valid | O1: disc_bucket | P1: net_revenue | Q1: profit_proxy | R1: new_discount | S1: is_capped | T1: discount_saved | U1: profit_new | V1: profit_scenario
A2: 3 | B2: Order Finished | C2: Muhammed Mac Intyre | D2: 40464 | E2: 6 | F2: 523080 | G2: 0.04 | H2: 20923 | I2: Office Supplies | J2: Storage & Organization | K2: =YEAR(D2) -> 2010 | L2: =IF(B2="Order Finished",1,0) -> 1 | M2: =IF(B2="Order Returned",1,0) -> 0 | N2: =IF(B2="Order Cancelled",0,1) -> 1 | O2: =IF(G2=0,"A: 0%",IF(G2<=0.03,"B: 1-3%",IF(G2<=0.06,"C: 4-6%","D: 7%+"))) -> C: 4-6% | P2: =IF(L2=1,F2-H2,0) -> 502157 | Q2: =IF(L2=1,F2*INDEX(Asumsi!$B$5:$B$7,MATCH(I2,Asumsi!$A$5:$A$7,0))-H2,0) -> 136001 | R2: =MIN(G2,INDEX(Asumsi!$C$5:$C$7,MATCH(I2,Asumsi!$A$5:$A$7,0))) -> 0.04 | S2: =IF(G2>R2,1,0) -> 0 | T2: =IF(L2=1,F2*(G2-R2),0) -> 0 | U2: =IF(L2=1,F2*INDEX(Asumsi!$B$5:$B$7,MATCH(I2,Asumsi!$A$5:$A$7,0))-F2*R2,0) -> 136000.8 | V2: =IF(S2=1,U2*(1-Asumsi!$B$10),U2) -> 136000.8
A3: 293 | B3: Order Finished | C3: Barry French | D3: 41183 | E3: 49 | F3: 20246040 | G3: 0.07 | H3: 1417223 | I3: Office Supplies | J3: Appliances | K3: =YEAR(D3) -> 2012 | L3: =IF(B3="Order Finished",1,0) -> 1 | M3: =IF(B3="Order Returned",1,0) -> 0 | N3: =IF(B3="Order Cancelled",0,1) -> 1 | O3: =IF(G3=0,"A: 0%",IF(G3<=0.03,"B: 1-3%",IF(G3<=0.06,"C: 4-6%","D: 7%+"))) -> D: 7%+ | P3: =IF(L3=1,F3-H3,0) -> 18828817 | Q3: =IF(L3=1,F3*INDEX(Asumsi!$B$5:$B$7,MATCH(I3,Asumsi!$A$5:$A$7,0))-H3,0) -> 4656589 | R3: =MIN(G3,INDEX(Asumsi!$C$5:$C$7,MATCH(I3,Asumsi!$A$5:$A$7,0))) -> 0.05 | S3: =IF(G3>R3,1,0) -> 1 | T3: =IF(L3=1,F3*(G3-R3),0) -> 404920.8 | U3: =IF(L3=1,F3*INDEX(Asumsi!$B$5:$B$7,MATCH(I3,Asumsi!$A$5:$A$7,0))-F3*R3,0) -> 5061510 | V3: =IF(S3=1,U3*(1-Asumsi!$B$10),U3) -> 4808434.5
A4: 483 | B4: Order Finished | C4: Clay Rozendal | D4: 40734 | E4: 30 | F4: 9931519 | G4: 0.08 | H4: 794522 | I4: Technology | J4: Telephones & Communication | K4: =YEAR(D4) -> 2011 | L4: =IF(B4="Order Finished",1,0) -> 1 | M4: =IF(B4="Order Returned",1,0) -> 0 | N4: =IF(B4="Order Cancelled",0,1) -> 1 | O4: =IF(G4=0,"A: 0%",IF(G4<=0.03,"B: 1-3%",IF(G4<=0.06,"C: 4-6%","D: 7%+"))) -> D: 7%+ | P4: =IF(L4=1,F4-H4,0) -> 9136997 | Q4: =IF(L4=1,F4*INDEX(Asumsi!$B$5:$B$7,MATCH(I4,Asumsi!$A$5:$A$7,0))-H4,0) -> 2184933.7 | R4: =MIN(G4,INDEX(Asumsi!$C$5:$C$7,MATCH(I4,Asumsi!$A$5:$A$7,0))) -> 0.05 | S4: =IF(G4>R4,1,0) -> 1 | T4: =IF(L4=1,F4*(G4-R4),0) -> 297945.57 | U4: =IF(L4=1,F4*INDEX(Asumsi!$B$5:$B$7,MATCH(I4,Asumsi!$A$5:$A$7,0))-F4*R4,0) -> 2482879.7 | V4: =IF(S4=1,U4*(1-Asumsi!$B$10),U4) -> 2358735.8
A5: 515 | B5: Order Finished | C5: Carlos Soltero | D5: 40418 | E5: 19 | F5: 788540 | G5: 0.08 | H5: 63083 | I5: Office Supplies | J5: Appliances | K5: =YEAR(D5) -> 2010 | L5: =IF(B5="Order Finished",1,0) -> 1 | M5: =IF(B5="Order Returned",1,0) -> 0 | N5: =IF(B5="Order Cancelled",0,1) -> 1 | O5: =IF(G5=0,"A: 0%",IF(G5<=0.03,"B: 1-3%",IF(G5<=0.06,"C: 4-6%","D: 7%+"))) -> D: 7%+ | P5: =IF(L5=1,F5-H5,0) -> 725457 | Q5: =IF(L5=1,F5*INDEX(Asumsi!$B$5:$B$7,MATCH(I5,Asumsi!$A$5:$A$7,0))-H5,0) -> 173479 | R5: =MIN(G5,INDEX(Asumsi!$C$5:$C$7,MATCH(I5,Asumsi!$A$5:$A$7,0))) -> 0.05 | S5: =IF(G5>R5,1,0) -> 1 | T5: =IF(L5=1,F5*(G5-R5),0) -> 23656.2 | U5: =IF(L5=1,F5*INDEX(Asumsi!$B$5:$B$7,MATCH(I5,Asumsi!$A$5:$A$7,0))-F5*R5,0) -> 197135 | V5: =IF(S5=1,U5*(1-Asumsi!$B$10),U5) -> 187278.25
A6: 613 | B6: Order Finished | C6: Carl Jackson | D6: 40711 | E6: 12 | F6: 187080 | G6: 0.03 | H6: 5612 | I6: Office Supplies | J6: Binders & Binder Accessories | K6: =YEAR(D6) -> 2011 | L6: =IF(B6="Order Finished",1,0) -> 1 | M6: =IF(B6="Order Returned",1,0) -> 0 | N6: =IF(B6="Order Cancelled",0,1) -> 1 | O6: =IF(G6=0,"A: 0%",IF(G6<=0.03,"B: 1-3%",IF(G6<=0.06,"C: 4-6%","D: 7%+"))) -> B: 1-3% | P6: =IF(L6=1,F6-H6,0) -> 181468 | Q6: =IF(L6=1,F6*INDEX(Asumsi!$B$5:$B$7,MATCH(I6,Asumsi!$A$5:$A$7,0))-H6,0) -> 50512 | R6: =MIN(G6,INDEX(Asumsi!$C$5:$C$7,MATCH(I6,Asumsi!$A$5:$A$7,0))) -> 0.03 | S6: =IF(G6>R6,1,0) -> 0 | T6: =IF(L6=1,F6*(G6-R6),0) -> 0 | U6: =IF(L6=1,F6*INDEX(Asumsi!$B$5:$B$7,MATCH(I6,Asumsi!$A$5:$A$7,0))-F6*R6,0) -> 50511.6 | V6: =IF(S6=1,U6*(1-Asumsi!$B$10),U6) -> 50511.6
A7: 643 | B7: Order Finished | C7: Monica Federle | D7: 40626 | E7: 21 | F7: 5563640 | G7: 0.07 | H7: 389455 | I7: Office Supplies | J7: Storage & Organization | K7: =YEAR(D7) -> 2011 | L7: =IF(B7="Order Finished",1,0) -> 1 | M7: =IF(B7="Order Returned",1,0) -> 0 | N7: =IF(B7="Order Cancelled",0,1) -> 1 | O7: =IF(G7=0,"A: 0%",IF(G7<=0.03,"B: 1-3%",IF(G7<=0.06,"C: 4-6%","D: 7%+"))) -> D: 7%+ | P7: =IF(L7=1,F7-H7,0) -> 5174185 | Q7: =IF(L7=1,F7*INDEX(Asumsi!$B$5:$B$7,MATCH(I7,Asumsi!$A$5:$A$7,0))-H7,0) -> 1279637 | R7: =MIN(G7,INDEX(Asumsi!$C$5:$C$7,MATCH(I7,Asumsi!$A$5:$A$7,0))) -> 0.05 | S7: =IF(G7>R7,1,0) -> 1 | T7: =IF(L7=1,F7*(G7-R7),0) -> 111272.8 | U7: =IF(L7=1,F7*INDEX(Asumsi!$B$5:$B$7,MATCH(I7,Asumsi!$A$5:$A$7,0))-F7*R7,0) -> 1390910 | V7: =IF(S7=1,U7*(1-Asumsi!$B$10),U7) -> 1321364.5
A8: 678 | B8: Order Returned | C8: Dorothy Badders | D8: 40235 | E8: 44 | F8: 456820 | G8: 0.07 | H8: 31977 | I8: Office Supplies | J8: Paper | K8: =YEAR(D8) -> 2010 | L8: =IF(B8="Order Finished",1,0) -> 0 | M8: =IF(B8="Order Returned",1,0) -> 1 | N8: =IF(B8="Order Cancelled",0,1) -> 1 | O8: =IF(G8=0,"A: 0%",IF(G8<=0.03,"B: 1-3%",IF(G8<=0.06,"C: 4-6%","D: 7%+"))) -> D: 7%+ | P8: =IF(L8=1,F8-H8,0) -> 0 | Q8: =IF(L8=1,F8*INDEX(Asumsi!$B$5:$B$7,MATCH(I8,Asumsi!$A$5:$A$7,0))-H8,0) -> 0 | R8: =MIN(G8,INDEX(Asumsi!$C$5:$C$7,MATCH(I8,Asumsi!$A$5:$A$7,0))) -> 0.05 | S8: =IF(G8>R8,1,0) -> 1 | T8: =IF(L8=1,F8*(G8-R8),0) -> 0 | U8: =IF(L8=1,F8*INDEX(Asumsi!$B$5:$B$7,MATCH(I8,Asumsi!$A$5:$A$7,0))-F8*R8,0) -> 0 | V8: =IF(S8=1,U8*(1-Asumsi!$B$10),U8) -> 0
A9: 807 | B9: Order Finished | C9: Neola Schneider | D9: 40505 | E9: 45 | F9: 393700 | G9: 0.01 | H9: 3937 | I9: Office Supplies | J9: Paper | K9: =YEAR(D9) -> 2010 | L9: =IF(B9="Order Finished",1,0) -> 1 | M9: =IF(B9="Order Returned",1,0) -> 0 | N9: =IF(B9="Order Cancelled",0,1) -> 1 | O9: =IF(G9=0,"A: 0%",IF(G9<=0.03,"B: 1-3%",IF(G9<=0.06,"C: 4-6%","D: 7%+"))) -> B: 1-3% | P9: =IF(L9=1,F9-H9,0) -> 389763 | Q9: =IF(L9=1,F9*INDEX(Asumsi!$B$5:$B$7,MATCH(I9,Asumsi!$A$5:$A$7,0))-H9,0) -> 114173 | R9: =MIN(G9,INDEX(Asumsi!$C$5:$C$7,MATCH(I9,Asumsi!$A$5:$A$7,0))) -> 0.01 | S9: =IF(G9>R9,1,0) -> 0 | T9: =IF(L9=1,F9*(G9-R9),0) -> 0 | U9: =IF(L9=1,F9*INDEX(Asumsi!$B$5:$B$7,MATCH(I9,Asumsi!$A$5:$A$7,0))-F9*R9,0) -> 114173 | V9: =IF(S9=1,U9*(1-Asumsi!$B$10),U9) -> 114173
A10: 868 | B10: Order Finished | C10: Carlos Daly | D10: 41068 | E10: 32 | F10: 1433680 | G10: 0 | H10: 0 | I10: Office Supplies | J10: Appliances | K10: =YEAR(D10) -> 2012 | L10: =IF(B10="Order Finished",1,0) -> 1 | M10: =IF(B10="Order Returned",1,0) -> 0 | N10: =IF(B10="Order Cancelled",0,1) -> 1 | O10: =IF(G10=0,"A: 0%",IF(G10<=0.03,"B: 1-3%",IF(G10<=0.06,"C: 4-6%","D: 7%+"))) -> A: 0% | P10: =IF(L10=1,F10-H10,0) -> 1433680 | Q10: =IF(L10=1,F10*INDEX(Asumsi!$B$5:$B$7,MATCH(I10,Asumsi!$A$5:$A$7,0))-H10,0) -> 430104 | R10: =MIN(G10,INDEX(Asumsi!$C$5:$C$7,MATCH(I10,Asumsi!$A$5:$A$7,0))) -> 0 | S10: =IF(G10>R10,1,0) -> 0 | T10: =IF(L10=1,F10*(G10-R10),0) -> 0 | U10: =IF(L10=1,F10*INDEX(Asumsi!$B$5:$B$7,MATCH(I10,Asumsi!$A$5:$A$7,0))-F10*R10,0) -> 430104 | V10: =IF(S10=1,U10*(1-Asumsi!$B$10),U10) -> 430104
A11: 933 | B11: Order Finished | C11: Claudia Miner | D11: 41125 | E11: 15 | F11: 161220 | G11: 0.02 | H11: 3224 | I11: Office Supplies | J11: Binders & Binder Accessories | K11: =YEAR(D11) -> 2012 | L11: =IF(B11="Order Finished",1,0) -> 1 | M11: =IF(B11="Order Returned",1,0) -> 0 | N11: =IF(B11="Order Cancelled",0,1) -> 1 | O11: =IF(G11=0,"A: 0%",IF(G11<=0.03,"B: 1-3%",IF(G11<=0.06,"C: 4-6%","D: 7%+"))) -> B: 1-3% | P11: =IF(L11=1,F11-H11,0) -> 157996 | Q11: =IF(L11=1,F11*INDEX(Asumsi!$B$5:$B$7,MATCH(I11,Asumsi!$A$5:$A$7,0))-H11,0) -> 45142 | R11: =MIN(G11,INDEX(Asumsi!$C$5:$C$7,MATCH(I11,Asumsi!$A$5:$A$7,0))) -> 0.02 | S11: =IF(G11>R11,1,0) -> 0 | T11: =IF(L11=1,F11*(G11-R11),0) -> 0 | U11: =IF(L11=1,F11*INDEX(Asumsi!$B$5:$B$7,MATCH(I11,Asumsi!$A$5:$A$7,0))-F11*R11,0) -> 45141.6 | V11: =IF(S11=1,U11*(1-Asumsi!$B$10),U11) -> 45141.6
A12: 995 | B12: Order Finished | C12: Neola Schneider | D12: 40693 | E12: 46 | F12: 3630980 | G12: 0.03 | H12: 108929 | I12: Furniture | J12: Office Furnishings | K12: =YEAR(D12) -> 2011 | L12: =IF(B12="Order Finished",1,0) -> 1 | M12: =IF(B12="Order Returned",1,0) -> 0 | N12: =IF(B12="Order Cancelled",0,1) -> 1 | O12: =IF(G12=0,"A: 0%",IF(G12<=0.03,"B: 1-3%",IF(G12<=0.06,"C: 4-6%","D: 7%+"))) -> B: 1-3% | P12: =IF(L12=1,F12-H12,0) -> 3522051 | Q12: =IF(L12=1,F12*INDEX(Asumsi!$B$5:$B$7,MATCH(I12,Asumsi!$A$5:$A$7,0))-H12,0) -> 980365 | R12: =MIN(G12,INDEX(Asumsi!$C$5:$C$7,MATCH(I12,Asumsi!$A$5:$A$7,0))) -> 0.03 | S12: =IF(G12>R12,1,0) -> 0 | T12: =IF(L12=1,F12*(G12-R12),0) -> 0 | U12: =IF(L12=1,F12*INDEX(Asumsi!$B$5:$B$7,MATCH(I12,Asumsi!$A$5:$A$7,0))-F12*R12,0) -> 980364.6 | V12: =IF(S12=1,U12*(1-Asumsi!$B$10),U12) -> 980364.6
A13: 998 | B13: Order Finished | C13: Allen Rosenblatt | D13: 40142 | E13: 16 | F13: 496520 | G13: 0.07 | H13: 34756 | I13: Office Supplies | J13: Envelopes | K13: =YEAR(D13) -> 2009 | L13: =IF(B13="Order Finished",1,0) -> 1 | M13: =IF(B13="Order Returned",1,0) -> 0 | N13: =IF(B13="Order Cancelled",0,1) -> 1 | O13: =IF(G13=0,"A: 0%",IF(G13<=0.03,"B: 1-3%",IF(G13<=0.06,"C: 4-6%","D: 7%+"))) -> D: 7%+ | P13: =IF(L13=1,F13-H13,0) -> 461764 | Q13: =IF(L13=1,F13*INDEX(Asumsi!$B$5:$B$7,MATCH(I13,Asumsi!$A$5:$A$7,0))-H13,0) -> 114200 | R13: =MIN(G13,INDEX(Asumsi!$C$5:$C$7,MATCH(I13,Asumsi!$A$5:$A$7,0))) -> 0.05 | S13: =IF(G13>R13,1,0) -> 1 | T13: =IF(L13=1,F13*(G13-R13),0) -> 9930.4 | U13: =IF(L13=1,F13*INDEX(Asumsi!$B$5:$B$7,MATCH(I13,Asumsi!$A$5:$A$7,0))-F13*R13,0) -> 124130 | V13: =IF(S13=1,U13*(1-Asumsi!$B$10),U13) -> 117923.5
... A5500: 56581 | B5500: Order Finished | C5500: Lisa De Cherney | D5500: 39852 | E5500: 20 | F5500: 4052020 | G5500: 0.1 | H5500: 405202 | I5500: Furniture | J5500: Office Furnishings | K5500: =YEAR(D5500) -> 2009 | L5500: =IF(B5500="Order Finished",1,0) -> 1 | M5500: =IF(B5500="Order Returned",1,0) -> 0 | N5500: =IF(B5500="Order Cancelled",0,1) -> 1 | O5500: =IF(G5500=0,"A: 0%",IF(G5500<=0.03,"B: 1-3%",IF(G5500<=0.06,"C: 4-6%","D: 7%+"))) -> D: 7%+ | P5500: =IF(L5500=1,F5500-H5500,0) -> 3646818 | Q5500: =IF(L5500=1,F5500*INDEX(Asumsi!$B$5:$B$7,MATCH(I5500,Asumsi!$A$5:$A$7,0))-H5500,0) -> 810404 | R5500: =MIN(G5500,INDEX(Asumsi!$C$5:$C$7,MATCH(I5500,Asumsi!$A$5:$A$7,0))) -> 0.03 | S5500: =IF(G5500>R5500,1,0) -> 1 | T5500: =IF(L5500=1,F5500*(G5500-R5500),0) -> 283641.4 | U5500: =IF(L5500=1,F5500*INDEX(Asumsi!$B$5:$B$7,MATCH(I5500,Asumsi!$A$5:$A$7,0))-F5500*R5500,0) -> 1094045.4 | V5500: =IF(S5500=1,U5500*(1-Asumsi!$B$10),U5500) -> 1039343.1
